tripmaster/__init__.py
tripmaster/core/__init__.py
tripmaster/core/app/__init__.py
tripmaster/core/app/config.py
tripmaster/core/app/io.py
tripmaster/core/app/pipeline.py
tripmaster/core/app/reinforce.py
tripmaster/core/app/standalone.py
tripmaster/core/app/supervise.py
tripmaster/core/components/__init__.py
tripmaster/core/components/backend.py
tripmaster/core/components/contract.py
tripmaster/core/components/evaluator.py
tripmaster/core/components/loss.py
tripmaster/core/components/problem.py
tripmaster/core/components/repo.py
tripmaster/core/components/task.py
tripmaster/core/components/environment/__init__.py
tripmaster/core/components/environment/base.py
tripmaster/core/components/environment/supervised.py
tripmaster/core/components/machine/__init__.py
tripmaster/core/components/machine/data_traits.py
tripmaster/core/components/machine/machine.py
tripmaster/core/components/machine/reinforce.py
tripmaster/core/components/modeler/__init__.py
tripmaster/core/components/modeler/machine_memory.py
tripmaster/core/components/modeler/memory_batch.py
tripmaster/core/components/modeler/modeler.py
tripmaster/core/components/operator/__init__.py
tripmaster/core/components/operator/multi_task.py
tripmaster/core/components/operator/operator.py
tripmaster/core/components/operator/reinforce.py
tripmaster/core/components/operator/supervise.py
tripmaster/core/components/operator/strategies/__init__.py
tripmaster/core/components/operator/strategies/batching.py
tripmaster/core/components/operator/strategies/distributed.py
tripmaster/core/components/operator/strategies/event_trigger.py
tripmaster/core/components/operator/strategies/exploration_strategy.py
tripmaster/core/components/operator/strategies/metric_logging.py
tripmaster/core/components/operator/strategies/model_selection.py
tripmaster/core/components/operator/strategies/optimization.py
tripmaster/core/concepts/__init__.py
tripmaster/core/concepts/component.py
tripmaster/core/concepts/contract.py
tripmaster-1.0.11.dist-info/LICENSE
tripmaster-1.0.11.dist-info/METADATA
tripmaster-1.0.11.dist-info/WHEEL
tripmaster-1.0.11.dist-info/top_level.txt
tripmaster-1.0.11.dist-info/RECORD
